hll_py/AutoCorrector.py
hll_py/Hasher.py
hll_py/HyperLogLog.py
hll_py/HyperLogLogLDP.py
hll_py/__init__.py
hll_py/compare.py
hll_py/test.py
hll_py/top3.py
hll_py-0.1.11.dist-info/METADATA
hll_py-0.1.11.dist-info/WHEEL
hll_py-0.1.11.dist-info/top_level.txt
hll_py-0.1.11.dist-info/RECORD
