Metadata-Version: 2.4
Name: hll_py
Version: 0.1.11
Summary: A Python library for fuzzy matching and local differentially private counting using probabilistic data structures like HyperLogLog.
License: MIT
Project-URL: Homepage, https://github.com/SY-David/AdvDS-Final-Project/tree/main/hll_py
Project-URL: Repository, https://github.com/SY-David/AdvDS-Final-Project/tree/main/hll_py
Requires-Python: >=3.7
